base/__init__.py
base/file/__init__.py
base/file/file_util.py
base/git/__init__.py
base/git/git_util.py
base/log/__init__.py
base/log/log_util.py
base/ninja/__init__.py
base/ninja/ninja_util.py
base/p4/__init__.py
base/p4/p4_util.py
base/reporter/__init__.py
base/reporter/blazecache_reporter.py
base/time_stamp/__init__.py
base/time_stamp/time_stamp_util.py
base/tos/__init__.py
base/tos/tos_util.py
base/track_report/__init__.py
base/track_report/track_report_util.py
blazecache/__init__.py
blazecache/blazecache.py
business/__init__.py
business/compilecachesubmit_plugin.py
business/postcompile_plugin.py
business/precompile_plugin.py
module/__init__.py
module/config/__init__.py
module/config/product_config.py
module/p4/__init__.py
module/p4/p4_manager.py
module/repo/__init__.py
module/repo/repo_manager.py
test/__init__.py
test/test_clickhouse.py
test/test_compile_cache_submit_plugin.py
test/test_electron_cache_submit.py
test/test_electron_precompile_plugin.py
test/test_precompile_plugin.py
blazecache-1.3.9.dist-info/METADATA
blazecache-1.3.9.dist-info/WHEEL
blazecache-1.3.9.dist-info/top_level.txt
blazecache-1.3.9.dist-info/RECORD
